[{"product_id":"NHP 8103 Silky Shine Hot & Cold Foldable Hair Dryer - 1300 Watt","product_name":"NHP 8103 Silky Shine Hot & Cold Foldable Hair Dryer - 1300 Watt","brand_name":"Nova","category":"Beauty & Hygiene","barcode":"890614171723756","price_per_unit":438,"unit_type":"Tools & Accessories","stock_quantity":161},{"product_id":"NHS 840 Pro Shine Hair Straightener","product_name":"NHS 840 Pro Shine Hair Straightener","brand_name":"Nova","category":"Beauty & Hygiene","barcode":"890614175749122","price_per_unit":418.6,"unit_type":"Tools & Accessories","stock_quantity":44},{"product_id":"NHT 1088 Prime Series Corded & Cordless Trimmer For Men","product_name":"NHT 1088 Prime Series Corded & Cordless Trimmer For Men","brand_name":"Nova","category":"Beauty & Hygiene","barcode":"890614179776918","price_per_unit":1053.6,"unit_type":"Moustache & Beard Care","stock_quantity":208},{"product_id":"NHP 8105 Silky Shine Hot & Cold Foldable Hair Dryer - 1200 Watt","product_name":"NHP 8105 Silky Shine Hot & Cold Foldable Hair Dryer - 1200 Watt","brand_name":"Nova","category":"Beauty & Hygiene","barcode":"890614181589382","price_per_unit":453.6,"unit_type":"Tools & Accessories","stock_quantity":197},{"product_id":"NHT 1045 Rechargeable Cordless Beard Trimmer for Men - Black","product_name":"NHT 1045 Rechargeable Cordless Beard Trimmer for Men - Black","brand_name":"Nova","category":"Beauty & Hygiene","barcode":"8906141834102336","price_per_unit":388.05,"unit_type":"Moustache & Beard Care","stock_quantity":299},{"product_id":"NHS 860 Temperature Control Professional Hair Straightener","product_name":"NHS 860 Temperature Control Professional Hair Straightener","brand_name":"Nova","category":"Beauty & Hygiene","barcode":"8906141838104394","price_per_unit":467.03,"unit_type":"Tools & Accessories","stock_quantity":94},{"product_id":"NHT 1072 Fast Charge Titanium Coated Cordless Trimmer For Men","product_name":"NHT 1072 Fast Charge Titanium Coated Cordless Trimmer For Men","brand_name":"Nova","category":"Beauty & Hygiene","barcode":"8906141846109933","price_per_unit":983.1,"unit_type":"Moustache & Beard Care","stock_quantity":152},{"product_id":"NHP 8100 Silky Shine Hot & Cold Foldable Hair Dryer - 1200 Watt","product_name":"NHP 8100 Silky Shine Hot & Cold Foldable Hair Dryer - 1200 Watt","brand_name":"Nova","category":"Beauty & Hygiene","barcode":"8906141869124051","price_per_unit":422.5,"unit_type":"Tools & Accessories","stock_quantity":95},{"product_id":"NHS-900 Temperature Control Professional Hair Straightener","product_name":"NHS-900 Temperature Control Professional Hair Straightener","brand_name":"Nova","category":"Beauty & Hygiene","barcode":"8906141912149760","price_per_unit":586.33,"unit_type":"Tools & Accessories","stock_quantity":58},{"product_id":"NHP 8104 Silky Shine Hot & Cold Foldable Hair Dryer - 1400 Watt","product_name":"NHP 8104 Silky Shine Hot & Cold Foldable Hair Dryer - 1400 Watt","brand_name":"Nova","category":"Beauty & Hygiene","barcode":"8906141938170002","price_per_unit":430.2,"unit_type":"Tools & Accessories","stock_quantity":70},{"product_id":"NHT 1055 BL Cordless Trimmer For Men","product_name":"NHT 1055 BL Cordless Trimmer For Men","brand_name":"Nova","category":"Beauty & Hygiene","barcode":"8906141939170366","price_per_unit":422.67,"unit_type":"Moustache & Beard Care","stock_quantity":103},{"product_id":"NHT 1020 Cordless Trimmer For Men - Black","product_name":"NHT 1020 Cordless Trimmer For Men - Black","brand_name":"Nova","category":"Beauty & Hygiene","barcode":"8906141944173348","price_per_unit":605.48,"unit_type":"Moustache & Beard Care","stock_quantity":35},{"product_id":"NHT 1080 Corded & Cordless Trimmer For Men","product_name":"NHT 1080 Corded & Cordless Trimmer For Men","brand_name":"Nova","category":"Beauty & Hygiene","barcode":"8906141953180734","price_per_unit":598,"unit_type":"Moustache & Beard Care","stock_quantity":93},{"product_id":"NHT 1089 Prime Series Corded & Cordless Trimmer For Men","product_name":"NHT 1089 Prime Series Corded & Cordless Trimmer For Men","brand_name":"Nova","category":"Beauty & Hygiene","barcode":"8906141963186312","price_per_unit":1170.45,"unit_type":"Moustache & Beard Care","stock_quantity":181},{"product_id":"NHT 1093 Trim & Shave Cordless Trimmer For Men - Black","product_name":"NHT 1093 Trim & Shave Cordless Trimmer For Men - Black","brand_name":"Nova","category":"Beauty & Hygiene","barcode":"8906141973191398","price_per_unit":1186.5,"unit_type":"Moustache & Beard Care","stock_quantity":153},{"product_id":"NHT 1047 B Cordless Trimmer For Men","product_name":"NHT 1047 B Cordless Trimmer For Men","brand_name":"Nova","category":"Beauty & Hygiene","barcode":"8906141980196974","price_per_unit":426.08,"unit_type":"Moustache & Beard Care","stock_quantity":171},{"product_id":"NHT 1091 Pro Cut Cordless Trimmer For MenÂ - Black","product_name":"NHT 1091 Pro Cut Cordless Trimmer For MenÂ - Black","brand_name":"Nova","category":"Beauty & Hygiene","barcode":"8906142012217984","price_per_unit":864.45,"unit_type":"Moustache & Beard Care","stock_quantity":291},{"product_id":"NHT 1046 Cordless Trimmer For Men","product_name":"NHT 1046 Cordless Trimmer For Men","brand_name":"Nova","category":"Beauty & Hygiene","barcode":"8906142033232812","price_per_unit":394.98,"unit_type":"Moustache & Beard Care","stock_quantity":138},{"product_id":"NHC 990 Hair Straightener","product_name":"NHC 990 Hair Straightener","brand_name":"Nova","category":"Beauty & Hygiene","barcode":"8906142043238948","price_per_unit":508.3,"unit_type":"Tools & Accessories","stock_quantity":115},{"product_id":"NHS 870 Temperature Control Professional Hair Straightener","product_name":"NHS 870 Temperature Control Professional Hair Straightener","brand_name":"Nova","category":"Beauty & Hygiene","barcode":"8906142084262217","price_per_unit":661.17,"unit_type":"Tools & Accessories","stock_quantity":190},{"product_id":"NHT 1049 Cordless Trimmer For Men","product_name":"NHT 1049 Cordless Trimmer For Men","brand_name":"Nova","category":"Beauty & Hygiene","barcode":"8906142102274569","price_per_unit":523.25,"unit_type":"Moustache & Beard Care","stock_quantity":47}]