[{"product_id":"Phyto-Rx Whitening & Brightening Face Wash","product_name":"Phyto-Rx Whitening & Brightening Face Wash","brand_name":"Lotus Professional","category":"Beauty & Hygiene","barcode":"890614169210213","price_per_unit":335.75,"unit_type":"Face Care","stock_quantity":260},{"product_id":"Phenyle - Black Disinfectant Fluid","product_name":"Phenyle - Black Disinfectant Fluid","brand_name":"Germisol","category":"Cleaning & Household","barcode":"890614173937502","price_per_unit":69,"unit_type":"Floor & Other Cleaners","stock_quantity":2},{"product_id":"Phyto-Rx Deep Pore Cleansing Face Wash","product_name":"Phyto-Rx Deep Pore Cleansing Face Wash","brand_name":"Lotus Professional","category":"Beauty & Hygiene","barcode":"890614174138959","price_per_unit":282,"unit_type":"Face Care","stock_quantity":41},{"product_id":"Phenyl - Mountain Magic (Herbal)","product_name":"Phenyl - Mountain Magic (Herbal)","brand_name":"Germisol","category":"Cleaning & Household","barcode":"890614176353027","price_per_unit":60,"unit_type":"Floor & Other Cleaners","stock_quantity":108},{"product_id":"Pheromone Activating Deodorant Spray For Men","product_name":"Pheromone Activating Deodorant Spray For Men","brand_name":"Skore","category":"Beauty & Hygiene","barcode":"890614182495906","price_per_unit":300,"unit_type":"Sexual Wellness","stock_quantity":142},{"product_id":"Phalkalyan Ghrita - For Women's Health","product_name":"Phalkalyan Ghrita - For Women's Health","brand_name":"Baidyanath","category":"Beauty & Hygiene","barcode":"8906141862120275","price_per_unit":280,"unit_type":"Ayurveda","stock_quantity":198},{"product_id":"Phenyle - Spice","product_name":"Phenyle - Spice","brand_name":"Germisol","category":"Cleaning & Household","barcode":"8906141884133358","price_per_unit":60,"unit_type":"Floor & Other Cleaners","stock_quantity":33},{"product_id":"Phoenix Fruit & Vegetable Plastic Basket - Assorted Colour","product_name":"Phoenix Fruit & Vegetable Plastic Basket - Assorted Colour","brand_name":"Aristo","category":"Cleaning & Household","barcode":"8906141899142540","price_per_unit":81,"unit_type":"Laundry, Storage Baskets","stock_quantity":160},{"product_id":"Phoenix Fruit & Vegetable Plastic Basket - Assorted Colour","product_name":"Phoenix Fruit & Vegetable Plastic Basket - Assorted Colour","brand_name":"Aristo","category":"Cleaning & Household","barcode":"8906141923157403","price_per_unit":109,"unit_type":"Laundry, Storage Baskets","stock_quantity":7},{"product_id":"Pheromone Activating Deodorant Spray For Men","product_name":"Pheromone Activating Deodorant Spray For Men","brand_name":"Skore","category":"Beauty & Hygiene","barcode":"8906141929163346","price_per_unit":300,"unit_type":"Sexual Wellness","stock_quantity":284},{"product_id":"Phenyl - Organic Floor Cleaner","product_name":"Phenyl - Organic Floor Cleaner","brand_name":"Gou Ganga","category":"Cleaning & Household","barcode":"8906141938170038","price_per_unit":320,"unit_type":"Floor & Other Cleaners","stock_quantity":147},{"product_id":"Phyto-Rx Daily Deep Cleansing Face Wash","product_name":"Phyto-Rx Daily Deep Cleansing Face Wash","brand_name":"Lotus Professional","category":"Beauty & Hygiene","barcode":"8906141940171300","price_per_unit":268,"unit_type":"Face Care","stock_quantity":92},{"product_id":"Phool Makhana","product_name":"Phool Makhana","brand_name":"bb Popular","category":"Foodgrains, Oil & Masala","barcode":"8906141951178663","price_per_unit":135,"unit_type":"Whole Spices","stock_quantity":279},{"product_id":"Phoenix Fruit & Vegetable Plastic Basket - Assorted Colour","product_name":"Phoenix Fruit & Vegetable Plastic Basket - Assorted Colour","brand_name":"Aristo","category":"Cleaning & Household","barcode":"8906141978195792","price_per_unit":154,"unit_type":"Laundry, Storage Baskets","stock_quantity":219},{"product_id":"Phenyl - Jasmine, Fresh","product_name":"Phenyl - Jasmine, Fresh","brand_name":"Venyaa","category":"Cleaning & Household","barcode":"8906141993206176","price_per_unit":75,"unit_type":"Floor & Other Cleaners","stock_quantity":231},{"product_id":"Phalasarpi - Uterine Disorders","product_name":"Phalasarpi - Uterine Disorders","brand_name":"Sri Sri Tattva","category":"Beauty & Hygiene","barcode":"8906141993206503","price_per_unit":160,"unit_type":"Ayurveda","stock_quantity":94},{"product_id":"Phantom Hot Tomato Ketchup Sauce - Made With World's Hottest Ghost Pepper","product_name":"Phantom Hot Tomato Ketchup Sauce - Made With World's Hottest Ghost Pepper","brand_name":"D-Alive","category":"Gourmet & World Food","barcode":"8906142024224877","price_per_unit":599,"unit_type":"Thai & Asian Sauces","stock_quantity":222},{"product_id":"Phool Makhana","product_name":"Phool Makhana","brand_name":"bb Royal","category":"Foodgrains, Oil & Masala","barcode":"8906142057247630","price_per_unit":145,"unit_type":"Whole Spices","stock_quantity":153},{"product_id":"Phenyle - Sensation (Herbal 2 in 1)","product_name":"Phenyle - Sensation (Herbal 2 in 1)","brand_name":"Germisol","category":"Cleaning & Household","barcode":"8906142076258038","price_per_unit":60,"unit_type":"Floor & Other Cleaners","stock_quantity":231},{"product_id":"Phenyle - Cool Cyan","product_name":"Phenyle - Cool Cyan","brand_name":"Germisol","category":"Cleaning & Household","barcode":"8906142098270635","price_per_unit":60,"unit_type":"Floor & Other Cleaners","stock_quantity":150}]